Jvis/__init__.py
Jvis/_t_sne.py
Jvis/distances.py
Jvis/jumap_.py
Jvis/layouts.py
Jvis/nndescent.py
Jvis/plot.py
Jvis/rp_tree.py
Jvis/sparse.py
Jvis/sparse_nndescent.py
Jvis/spectral.py
Jvis/utils.py
Jvis/validation.py
Jvis_learn-0.0.12.dist-info/LICENSE.txt
Jvis_learn-0.0.12.dist-info/METADATA
Jvis_learn-0.0.12.dist-info/WHEEL
Jvis_learn-0.0.12.dist-info/top_level.txt
Jvis_learn-0.0.12.dist-info/RECORD
