Metadata-Version: 2.1
Name: Jvis-learn
Version: 0.0.12
Summary: A generalization of t-SNE and UMAP to single-cell multimodal omics
Home-page: https://github.com/canzarlab/Jvis-learn
Maintainer: Van Hoan Do
Maintainer-email: vanhoan310@gmail.com
License: BSD
Keywords: dimension reduction t-sne umap manifold multimodal data
Platform: UNKNOWN
Classifier: Development Status :: 3 - Alpha
Classifier: Intended Audience :: Science/Research
Classifier: Intended Audience :: Developers
Classifier: License :: OSI Approved
Classifier: Programming Language :: C
Classifier: Programming Language :: Python
Classifier: Topic :: Software Development
Classifier: Topic :: Scientific/Engineering
Classifier: Operating System :: Microsoft :: Windows
Classifier: Operating System :: POSIX
Classifier: Operating System :: Unix
Classifier: Operating System :: MacOS
Classifier: Programming Language :: Python :: 3.7
Classifier: Programming Language :: Python :: 3.6
Classifier: Programming Language :: Python :: 3.8
Requires-Dist: numpy (>=1.17)
Requires-Dist: scikit-learn (<=0.24.1,>=0.23.0)
Requires-Dist: scipy (>=1.3.1)
Requires-Dist: numba (!=0.47,>=0.46)
Provides-Extra: performance
Requires-Dist: pynndescent (>=0.4) ; extra == 'performance'
Requires-Dist: tbb (>=2019.5) ; extra == 'performance'
Provides-Extra: plot
Requires-Dist: pandas ; extra == 'plot'
Requires-Dist: matplotlib ; extra == 'plot'
Requires-Dist: datashader ; extra == 'plot'
Requires-Dist: bokeh ; extra == 'plot'
Requires-Dist: holoviews ; extra == 'plot'
Requires-Dist: colorcet ; extra == 'plot'
